setup.cfg
setup.py
djesrf/__init__.py
djesrf/models.py
djesrf/viewsets.py
djesrf.egg-info/PKG-INFO
djesrf.egg-info/SOURCES.txt
djesrf.egg-info/dependency_links.txt
djesrf.egg-info/requires.txt
djesrf.egg-info/top_level.txt