Metadata-Version: 1.0
Name: djesrf
Version: 1.0.4
Summary: DJES + DRF = AWESOME!!!
Home-page: https://github.com/theonion/djesrf
Author: Vince Forgione
Author-email: vforgione@theonion.com
License: MIT
Platform: UNKNOWN
